dirtrace/__init__.py
dirtrace/dirtrace.py
dirtrace-0.0.5.dist-info/LICENSE
dirtrace-0.0.5.dist-info/METADATA
dirtrace-0.0.5.dist-info/WHEEL
dirtrace-0.0.5.dist-info/entry_points.txt
dirtrace-0.0.5.dist-info/top_level.txt
dirtrace-0.0.5.dist-info/RECORD
